odoo/addons/sale_loyalty_order_info/README.rst
odoo/addons/sale_loyalty_order_info/__init__.py
odoo/addons/sale_loyalty_order_info/__manifest__.py
odoo/addons/sale_loyalty_order_info/i18n/it.po
odoo/addons/sale_loyalty_order_info/i18n/sale_loyalty_order_info.pot
odoo/addons/sale_loyalty_order_info/models/__init__.py
odoo/addons/sale_loyalty_order_info/models/sale_order.py
odoo/addons/sale_loyalty_order_info/readme/CONTRIBUTORS.rst
odoo/addons/sale_loyalty_order_info/readme/DESCRIPTION.rst
odoo/addons/sale_loyalty_order_info/static/description/icon.png
odoo/addons/sale_loyalty_order_info/static/description/index.html
odoo/addons/sale_loyalty_order_info/tests/__init__.py
odoo/addons/sale_loyalty_order_info/tests/test_sale_order.py
odoo_addon_sale_loyalty_order_info-16.0.1.0.0.4.dist-info/METADATA
odoo_addon_sale_loyalty_order_info-16.0.1.0.0.4.dist-info/WHEEL
odoo_addon_sale_loyalty_order_info-16.0.1.0.0.4.dist-info/top_level.txt
odoo_addon_sale_loyalty_order_info-16.0.1.0.0.4.dist-info/RECORD
